{
    "code": 200,
    "url":"http://www.kuwo.cn/api/pc/classify/playlist/getRcmPlayList?loginUid=1418640818&loginSid=3254760819&pn=1&rn=30&order=hot&httpsStatus=1&reqId=68ea5420-c185-11ea-bf4f-91fcf080bdf5",
    "curTime": 1594259047700,
    "data": {
        "total": 1377,
        "data": [
            {
                "img": "https://img1.kuwo.cn/star/userpl2015/81/23/1568111446441_182253281_500.jpg",
                "uname": "第一天",
                "lossless_mark": "0",
                "favorcnt": "25720",
                "isnew": "",
                "extend": "",
                "uid": "182253281",
                "total": "213",
                "commentcnt": "",
                "imgscript": "",
                "digest": "8",
                "name": "抖友看过来！点击获取热门歌曲合集！",
                "listencnt": "19940886",
                "id": "2851119330",
                "attribute": "",
                "radio_id": "",
                "desc": "",
                "info": ""
            },
            {
                "img": "https://img1.kuwo.cn/star/userpl2015/94/43/1571393589492_264384394_500.jpg",
                "uname": "Hawar",
                "lossless_mark": "0",
                "favorcnt": "1818",
                "isnew": "",
                "extend": "",
                "uid": "264384394",
                "total": "15",
                "commentcnt": "",
                "imgscript": "",
                "digest": "8",
                "name": "生命在于运动，音乐在于节奏",
                "listencnt": "121678353",
                "id": "2884170702",
                "attribute": "",
                "radio_id": "",
                "desc": "",
                "info": ""
            },
            {
                "img": "https://img1.kuwo.cn/star/userpl2015/47/81/1571647403052_458076447_500.jpg",
                "uname": "酷酷酷小我",
                "lossless_mark": "0",
                "favorcnt": "2138",
                "isnew": "",
                "extend": "",
                "uid": "458076447",
                "total": "20",
                "commentcnt": "",
                "imgscript": "",
                "digest": "8",
                "name": "追你，是真心实意",
                "listencnt": "80540643",
                "id": "2867664412",
                "attribute": "",
                "radio_id": "",
                "desc": "",
                "info": ""
            },
            {
                "img": "https://img1.kuwo.cn/star/userpl2015/15/39/1575620378567_448007115_500.jpg",
                "uname": "腾讯音乐人",
                "lossless_mark": "0",
                "favorcnt": "4304",
                "isnew": "",
                "extend": "",
                "uid": "448007115",
                "total": "26",
                "commentcnt": "",
                "imgscript": "",
                "digest": "8",
                "name": "都市民谣｜低吟浅唱，拨动心弦",
                "listencnt": "53195186",
                "id": "2919479799",
                "attribute": "",
                "radio_id": "",
                "desc": "",
                "info": ""
            },
            {
                "img": "https://img1.kuwo.cn/star/userpl2015/98/82/1587870043089_121006198_500.jpg",
                "uname": "念安娜",
                "lossless_mark": "0",
                "favorcnt": "2836",
                "isnew": "",
                "extend": "",
                "uid": "121006198",
                "total": "36",
                "commentcnt": "",
                "imgscript": "",
                "digest": "8",
                "name": "失恋听情歌｜不眠夜里的孤单心事",
                "listencnt": "1371606",
                "id": "3001661381",
                "attribute": "",
                "radio_id": "",
                "desc": "",
                "info": ""
            },
            {
                "img": "https://img1.kuwo.cn/star/userpl2015/34/63/1591954838229_153918234_500.jpg",
                "uname": "彧椛",
                "lossless_mark": "0",
                "favorcnt": "4668",
                "isnew": "",
                "extend": "",
                "uid": "153918234",
                "total": "35",
                "commentcnt": "",
                "imgscript": "",
                "digest": "8",
                "name": "2020热门DJ嗨曲，一键开启提速模式",
                "listencnt": "2113742",
                "id": "3009338189",
                "attribute": "",
                "radio_id": "",
                "desc": "",
                "info": ""
            },
            {
                "img": "https://img1.kuwo.cn/star/userpl2015/15/39/1573201778710_448007115_500.jpg",
                "uname": "腾讯音乐人",
                "lossless_mark": "0",
                "favorcnt": "3022",
                "isnew": "",
                "extend": "",
                "uid": "448007115",
                "total": "26",
                "commentcnt": "",
                "imgscript": "",
                "digest": "8",
                "name": "光棍节｜不再拥有你，不如与孤寂作伴",
                "listencnt": "53274617",
                "id": "2901369670",
                "attribute": "",
                "radio_id": "",
                "desc": "",
                "info": ""
            },
            {
                "img": "https://img1.kuwo.cn/star/userpl2015/98/82/1562548519997_121006198_500.jpg",
                "uname": "念安娜",
                "lossless_mark": "0",
                "favorcnt": "1793",
                "isnew": "",
                "extend": "",
                "uid": "121006198",
                "total": "132",
                "commentcnt": "",
                "imgscript": "",
                "digest": "8",
                "name": "网络精选｜这些情歌走心又易懂",
                "listencnt": "1151821",
                "id": "2813797704",
                "attribute": "",
                "radio_id": "",
                "desc": "",
                "info": ""
            },
            {
                "img": "https://img1.kuwo.cn/star/userpl2015/79/73/1578291144983_496840879_500.jpg",
                "uname": "我们都是有歌的人",
                "lossless_mark": "0",
                "favorcnt": "2102",
                "isnew": "",
                "extend": "",
                "uid": "496840879",
                "total": "20",
                "commentcnt": "",
                "imgscript": "",
                "digest": "8",
                "name": "惊艳年会｜我本淑女，别逼我疯狂",
                "listencnt": "21540865",
                "id": "2934713089",
                "attribute": "",
                "radio_id": "",
                "desc": "",
                "info": ""
            },
            {
                "img": "https://img1.kuwo.cn/star/userpl2015/3/90/1591687843326_189029403_500.jpg",
                "uname": "摘朵白莲花",
                "lossless_mark": "0",
                "favorcnt": "2620",
                "isnew": "",
                "extend": "",
                "uid": "189029403",
                "total": "146",
                "commentcnt": "",
                "imgscript": "",
                "digest": "8",
                "name": "抖音2020年6月热门BGM",
                "listencnt": "1325879",
                "id": "3025358234",
                "attribute": "",
                "radio_id": "",
                "desc": "",
                "info": ""
            },
            {
                "img": "https://img1.kuwo.cn/star/userpl2015/15/39/1582620290507_448007115_500.jpg",
                "uname": "腾讯音乐人",
                "lossless_mark": "0",
                "favorcnt": "3199",
                "isnew": "",
                "extend": "",
                "uid": "448007115",
                "total": "25",
                "commentcnt": "",
                "imgscript": "",
                "digest": "8",
                "name": "民谣男声|屏蔽纷纷扰扰",
                "listencnt": "10531851",
                "id": "2964988930",
                "attribute": "",
                "radio_id": "",
                "desc": "",
                "info": ""
            },
            {
                "img": "https://img1.kuwo.cn/star/userpl2015/15/39/1583130341034_448007115_500.jpg",
                "uname": "腾讯音乐人",
                "lossless_mark": "0",
                "favorcnt": "1747",
                "isnew": "",
                "extend": "",
                "uid": "448007115",
                "total": "20",
                "commentcnt": "",
                "imgscript": "",
                "digest": "8",
                "name": "所有的美好，都与你有关",
                "listencnt": "9716948",
                "id": "2966749992",
                "attribute": "",
                "radio_id": "",
                "desc": "",
                "info": ""
            },
            {
                "img": "https://img1.kuwo.cn/star/userpl2015/81/23/1559477523061_182253281_500.jpg",
                "uname": "第一天",
                "lossless_mark": "0",
                "favorcnt": "16882",
                "isnew": "",
                "extend": "",
                "uid": "182253281",
                "total": "61",
                "commentcnt": "",
                "imgscript": "",
                "digest": "8",
                "name": "抖音2019年5月热门BGM",
                "listencnt": "30377177",
                "id": "2780722826",
                "attribute": "",
                "radio_id": "",
                "desc": "",
                "info": ""
            },
            {
                "img": "https://img1.kuwo.cn/star/userpl2015/15/39/1582015331249_448007115_500.jpg",
                "uname": "腾讯音乐人",
                "lossless_mark": "0",
                "favorcnt": "2100",
                "isnew": "",
                "extend": "",
                "uid": "448007115",
                "total": "28",
                "commentcnt": "",
                "imgscript": "",
                "digest": "8",
                "name": "焦虑再见！春日活力满满",
                "listencnt": "10045842",
                "id": "2952935209",
                "attribute": "",
                "radio_id": "",
                "desc": "",
                "info": ""
            },
            {
                "img": "https://img1.kuwo.cn/star/userpl2015/79/73/1576221535780_496840879_500.jpg",
                "uname": "我们都是有歌的人",
                "lossless_mark": "0",
                "favorcnt": "3686",
                "isnew": "",
                "extend": "",
                "uid": "496840879",
                "total": "20",
                "commentcnt": "",
                "imgscript": "",
                "digest": "8",
                "name": "DJ嗨曲｜这节奏要飘了",
                "listencnt": "15250704",
                "id": "2916702953",
                "attribute": "",
                "radio_id": "",
                "desc": "",
                "info": ""
            },
            {
                "img": "https://img1.kuwo.cn/star/userpl2015/98/82/1592894276201_121006198_500.jpg",
                "uname": "念安娜",
                "lossless_mark": "0",
                "favorcnt": "1660",
                "isnew": "",
                "extend": "",
                "uid": "121006198",
                "total": "35",
                "commentcnt": "",
                "imgscript": "",
                "digest": "8",
                "name": "只要有想见的人，就不是孤身一人",
                "listencnt": "670332",
                "id": "3029730348",
                "attribute": "",
                "radio_id": "",
                "desc": "",
                "info": ""
            },
            {
                "img": "https://img1.kuwo.cn/star/userpl2015/37/49/1567049923819_183963037_500.jpg",
                "uname": "童年小伙伴",
                "lossless_mark": "0",
                "favorcnt": "6324",
                "isnew": "",
                "extend": "",
                "uid": "183963037",
                "total": "99",
                "commentcnt": "",
                "imgscript": "",
                "digest": "8",
                "name": "播歌量最高的儿歌100首",
                "listencnt": "4252824",
                "id": "777462942",
                "attribute": "",
                "radio_id": "",
                "desc": "",
                "info": ""
            },
            {
                "img": "https://img1.kuwo.cn/star/userpl2015/79/73/1578020621229_496840879_500.jpg",
                "uname": "我们都是有歌的人",
                "lossless_mark": "0",
                "favorcnt": "1431",
                "isnew": "",
                "extend": "",
                "uid": "496840879",
                "total": "20",
                "commentcnt": "",
                "imgscript": "",
                "digest": "8",
                "name": "寂寞不打烊｜午夜Disco专场",
                "listencnt": "12843388",
                "id": "2932836298",
                "attribute": "",
                "radio_id": "",
                "desc": "",
                "info": ""
            },
            {
                "img": "https://img1.kuwo.cn/star/userpl2015/43/57/1512722931619_414900543_500.jpg",
                "uname": "多喝白开水",
                "lossless_mark": "0",
                "favorcnt": "104502",
                "isnew": "",
                "extend": "",
                "uid": "414900543",
                "total": "276",
                "commentcnt": "",
                "imgscript": "",
                "digest": "8",
                "name": "【抖音】好听洗脑的BGM",
                "listencnt": "69316036",
                "id": "2359855649",
                "attribute": "",
                "radio_id": "",
                "desc": "",
                "info": ""
            },
            {
                "img": "https://img1.kuwo.cn/star/userpl2015/81/23/1557039794987_182253281_500.jpg",
                "uname": "第一天",
                "lossless_mark": "0",
                "favorcnt": "18764",
                "isnew": "",
                "extend": "",
                "uid": "182253281",
                "total": "57",
                "commentcnt": "",
                "imgscript": "",
                "digest": "8",
                "name": "抖音2019年4月热门BGM",
                "listencnt": "30370407",
                "id": "2754476893",
                "attribute": "",
                "radio_id": "",
                "desc": "",
                "info": ""
            },
            {
                "img": "https://img1.kuwo.cn/star/userpl2015/15/39/1573810068657_448007115_500.jpg",
                "uname": "腾讯音乐人",
                "lossless_mark": "0",
                "favorcnt": "2452",
                "isnew": "",
                "extend": "",
                "uid": "448007115",
                "total": "24",
                "commentcnt": "",
                "imgscript": "",
                "digest": "8",
                "name": "抒情民谣｜吉他声里讲述的爱情",
                "listencnt": "15778941",
                "id": "2906215789",
                "attribute": "",
                "radio_id": "",
                "desc": "",
                "info": ""
            },
            {
                "img": "https://img1.kuwo.cn/star/userpl2015/89/78/1533294815595_223778589_500.jpg",
                "uname": "Epicmusician",
                "lossless_mark": "0",
                "favorcnt": "24275",
                "isnew": "",
                "extend": "",
                "uid": "223778589",
                "total": "46",
                "commentcnt": "",
                "imgscript": "",
                "digest": "8",
                "name": "【欧美男声】柔情大叔，最为致命～",
                "listencnt": "47314188",
                "id": "2543304320",
                "attribute": "",
                "radio_id": "",
                "desc": "",
                "info": ""
            },
            {
                "img": "https://img1.kuwo.cn/star/userpl2015/81/23/1554102169483_182253281_500.jpg",
                "uname": "第一天",
                "lossless_mark": "0",
                "favorcnt": "22259",
                "isnew": "",
                "extend": "",
                "uid": "182253281",
                "total": "57",
                "commentcnt": "",
                "imgscript": "",
                "digest": "8",
                "name": "抖音2019年3月热门BGM",
                "listencnt": "28615189",
                "id": "2709933030",
                "attribute": "",
                "radio_id": "",
                "desc": "",
                "info": ""
            },
            {
                "img": "https://img1.kuwo.cn/star/userpl2015/81/23/1570783065082_182253281_500.jpg",
                "uname": "第一天",
                "lossless_mark": "0",
                "favorcnt": "13579",
                "isnew": "",
                "extend": "",
                "uid": "182253281",
                "total": "50",
                "commentcnt": "",
                "imgscript": "",
                "digest": "8",
                "name": "抖音2019年9月热门BGM",
                "listencnt": "13650944",
                "id": "2875088558",
                "attribute": "",
                "radio_id": "",
                "desc": "",
                "info": ""
            },
            {
                "img": "https://img1.kuwo.cn/star/userpl2015/15/39/1575620465938_448007115_500.jpg",
                "uname": "腾讯音乐人",
                "lossless_mark": "0",
                "favorcnt": "2154",
                "isnew": "",
                "extend": "",
                "uid": "448007115",
                "total": "32",
                "commentcnt": "",
                "imgscript": "",
                "digest": "8",
                "name": "等一场大雪，听你的故事",
                "listencnt": "10742564",
                "id": "2919192216",
                "attribute": "",
                "radio_id": "",
                "desc": "",
                "info": ""
            },
            {
                "img": "https://img1.kuwo.cn/star/userpl2015/95/40/1585800871205_254780995_500.jpg",
                "uname": "浣尽相思",
                "lossless_mark": "0",
                "favorcnt": "8975",
                "isnew": "",
                "extend": "",
                "uid": "254780995",
                "total": "36",
                "commentcnt": "",
                "imgscript": "",
                "digest": "8",
                "name": "【抖音】古风换装神曲，get国潮范儿",
                "listencnt": "3805059",
                "id": "2986675739",
                "attribute": "",
                "radio_id": "",
                "desc": "",
                "info": ""
            },
            {
                "img": "https://img1.kuwo.cn/star/userpl2015/81/23/1552024828822_182253281_500.jpg",
                "uname": "第一天",
                "lossless_mark": "0",
                "favorcnt": "11894",
                "isnew": "",
                "extend": "",
                "uid": "182253281",
                "total": "36",
                "commentcnt": "",
                "imgscript": "",
                "digest": "8",
                "name": "抖音最新网红音乐（三月第一周）",
                "listencnt": "24777024",
                "id": "2702751857",
                "attribute": "",
                "radio_id": "",
                "desc": "",
                "info": ""
            },
            {
                "img": "https://img1.kuwo.cn/star/userpl2015/11/54/1576570289830_447949611_500.jpg",
                "uname": "顾怀安",
                "lossless_mark": "0",
                "favorcnt": "3753",
                "isnew": "",
                "extend": "",
                "uid": "447949611",
                "total": "21",
                "commentcnt": "",
                "imgscript": "",
                "digest": "8",
                "name": "音乐巴士 · 独享下班生活",
                "listencnt": "8972465",
                "id": "2925452807",
                "attribute": "",
                "radio_id": "",
                "desc": "",
                "info": ""
            },
            {
                "img": "https://img1.kuwo.cn/star/userpl2015/81/23/1562660901237_182253281_500.jpg",
                "uname": "第一天",
                "lossless_mark": "0",
                "favorcnt": "10059",
                "isnew": "",
                "extend": "",
                "uid": "182253281",
                "total": "55",
                "commentcnt": "",
                "imgscript": "",
                "digest": "8",
                "name": "抖音2019年6月热门BGM",
                "listencnt": "16663668",
                "id": "2815194854",
                "attribute": "",
                "radio_id": "",
                "desc": "",
                "info": ""
            },
            {
                "img": "https://img1.kuwo.cn/star/userpl2015/47/81/1571647369784_458076447_500.jpg",
                "uname": "酷酷酷小我",
                "lossless_mark": "0",
                "favorcnt": "1872",
                "isnew": "",
                "extend": "",
                "uid": "458076447",
                "total": "20",
                "commentcnt": "",
                "imgscript": "",
                "digest": "8",
                "name": "离不开Darling 更离不开你",
                "listencnt": "11629723",
                "id": "2862709248",
                "attribute": "",
                "radio_id": "",
                "desc": "",
                "info": ""
            }
        ],
        "rn": 30,
        "pn": 1
    },
    "msg": "success",
    "profileId": "site",
    "reqId": "e6b79f2acaafe4dd5031e763d6c98ba3"
}